numerical_py/__init__.py
numerical_py/derivative.py
numerical_py/differentional.py
numerical_py/eigenvals.py
numerical_py/equations.py
numerical_py/integrals.py
numerical_py/interpolation.py
numerical_py/utils.py
numerical_py-1.0.0.dist-info/METADATA
numerical_py-1.0.0.dist-info/WHEEL
numerical_py-1.0.0.dist-info/top_level.txt
numerical_py-1.0.0.dist-info/RECORD
