Metadata-Version: 2.1
Name: numerical-py
Version: 1.0.0
Summary: Library for Numerical Methods Exam
Author: Aleksey Malakhov
License: MIT
